zeitsprung/__init__.py
zeitsprung/base.py
zeitsprung/database.py
zeitsprung/scraping.py
zeitsprung-0.1.1.dist-info/AUTHORS.rst
zeitsprung-0.1.1.dist-info/LICENSE
zeitsprung-0.1.1.dist-info/METADATA
zeitsprung-0.1.1.dist-info/WHEEL
zeitsprung-0.1.1.dist-info/top_level.txt
zeitsprung-0.1.1.dist-info/RECORD
