Metadata-Version: 2.1
Name: zeitsprung
Version: 0.1.1
Summary: Scraper for www.zeitsprung.fm, a great history podcast.
Home-page: https://github.com/munterfi/zeitsprung
Author: Merlin Unterfinger
Author-email: info@munterfinger.ch
License: MIT license
Keywords: zeitsprung
Platform: UNKNOWN
Classifier: Development Status :: 2 - Pre-Alpha
Classifier: Intended Audience :: Developers
Classifier: License :: OSI Approved :: MIT License
Classifier: Natural Language :: English
Classifier: Programming Language :: Python :: 3
Classifier: Programming Language :: Python :: 3.7
Classifier: Programming Language :: Python :: 3.8
Requires-Python: >=3.5
License-File: LICENSE
License-File: AUTHORS.rst
Requires-Dist: beautifulsoup4
Requires-Dist: pandas
Requires-Dist: pydub
Requires-Dist: requests
